netwitness/__init__.py
netwitness/constants.py
netwitness/models.py
netwitness/mongo.py
netwitness-0.1.0.dist-info/WHEEL
netwitness-0.1.0.dist-info/METADATA
netwitness-0.1.0.dist-info/RECORD
