Metadata-Version: 2.1
Name: netwitness
Version: 0.1.0
Summary: 
Author: Sean Drzewiecki
Author-email: sean.drzewiecki@netwitness.com
Requires-Python: >=3.6.8,<4.0.0
Classifier: Programming Language :: Python :: 3
Classifier: Programming Language :: Python :: 3.10
Classifier: Programming Language :: Python :: 3.7
Classifier: Programming Language :: Python :: 3.8
Classifier: Programming Language :: Python :: 3.9
Requires-Dist: aiohttp (>=3.8.1,<4.0.0)
Requires-Dist: motor (>=2.5.1,<3.0.0)
Requires-Dist: pydantic (>=1.9.0,<2.0.0)
